LICENSE
MANIFEST.in
README.rst
setup.py
seria/__init__.py
seria/cli.py
seria/compat.py
seria/providers.py
seria/serializers.py
seria/utils.py
seria.egg-info/PKG-INFO
seria.egg-info/SOURCES.txt
seria.egg-info/dependency_links.txt
seria.egg-info/entry_points.txt
seria.egg-info/requires.txt
seria.egg-info/top_level.txt
tests/test_cli.py
tests/test_seria.py
tests/test_utils.py
tests/__pycache__/test_cli.cpython-27-PYTEST.pyc
tests/__pycache__/test_seria.cpython-27-PYTEST.pyc
tests/__pycache__/test_utils.cpython-27-PYTEST.pyc
tests/resources/bad.json
tests/resources/bad.xml
tests/resources/bad.yaml
tests/resources/good.json
tests/resources/good.xml
tests/resources/good.yaml